trulyrandom/__init__.py
trulyrandom/main.py
trulyrandom-0.0.2.dist-info/METADATA
trulyrandom-0.0.2.dist-info/WHEEL
trulyrandom-0.0.2.dist-info/top_level.txt
trulyrandom-0.0.2.dist-info/RECORD
