Metadata-Version: 2.1
Name: trulyrandom
Version: 0.0.2
Summary: random.org API Implementation in Python
Home-page: UNKNOWN
Author: Envoy-VC (Vedant Chainani)
Author-email: vedantchainani1084@gmail.com
License: UNKNOWN
Keywords: python,random,api,json
Platform: UNKNOWN
Classifier: Development Status :: 1 - Planning
Classifier: Intended Audience :: Developers
Classifier: Programming Language :: Python :: 3
Classifier: Operating System :: Unix
Classifier: Operating System :: MacOS :: MacOS X
Classifier: Operating System :: Microsoft :: Windows
Requires-Dist: requests
